autocommit/__init__.py
autocommit/__main__.py
autocommit/build_ragdb.py
autocommit/commands.py
autocommit/config.py
autocommit/git_hooks.py
autocommit/mistral_model.py
autocommit/prompts/exchange_prompt.txt
autocommit/prompts/final_prompt.txt
autocommit/prompts/not_separated_prompt.txt
autocommit/prompts/start_prompt.txt
autocommit/prompts/system_prompt.txt
autocommit/prompts/title_prompt.txt
autocommit/setup.py
autocommit/utils.py
basic_rag/__init__.py
basic_rag/basic_rag.py
basic_rag/utils.py
mistral_tools/__init__.py
mistral_tools/conversation.py
mistral_tools/embeddings.py
mistral_tools/tool_register.py
mistral_tools/utils.py
git_autocommit_hook-0.1.2.dist-info/METADATA
git_autocommit_hook-0.1.2.dist-info/WHEEL
git_autocommit_hook-0.1.2.dist-info/entry_points.txt
git_autocommit_hook-0.1.2.dist-info/RECORD
