Metadata-Version: 2.1
Name: git_autocommit_hook
Version: 0.1.2
Summary: Automatically generate commit messages from changes
License: CECILL-B
Author: Tristan Brugère
Author-email: 67050900+tbrugere@users.noreply.github.com
Requires-Python: >=3.10,<4.0
Classifier: License :: CeCILL-B Free Software License Agreement (CECILL-B)
Classifier: Programming Language :: Python :: 3
Classifier: Programming Language :: Python :: 3.10
Classifier: Programming Language :: Python :: 3.11
Classifier: Programming Language :: Python :: 3.12
Classifier: Programming Language :: Python :: 3.13
Requires-Dist: faiss-cpu (>=1.9.0.post1,<2.0.0)
Requires-Dist: mistral-common (>=1.5.1,<2.0.0)
Requires-Dist: mistralai (>=1.2.3,<2.0.0)
Requires-Dist: pydantic (>=2.10.3,<3.0.0)
Requires-Dist: pygit2 (>=1.16.0,<2.0.0)
